[{"__type__":"cc.SpriteFrame","content":{"name":"egg_progress_bg","texture":"145411f13","rect":[1080,1680,230,125],"offset":[0,0],"originalSize":[230,125],"rotated":1,"capInsets":[66,0,62,0]}},{"__type__":"cc.SpriteFrame","content":{"name":"skill3","texture":"1f90e2f9a","rect":[1738,1874,122,122],"offset":[0,0],"originalSize":[122,122],"capInsets":[0,0,0,0]}},{"__type__":"cc.SpriteFrame","content":{"name":"skill_floor","texture":"145411f13","rect":[3,1222,74,74],"offset":[0,0],"originalSize":[74,74],"capInsets":[0,0,0,0]}},{"__type__":"cc.SpriteFrame","content":{"name":"tips_floor","texture":"11373946f","rect":[163,3,92,74],"offset":[0,0],"originalSize":[92,74],"rotated":1,"capInsets":[22,19,23,22]}},{"__type__":"cc.SpriteFrame","content":{"name":"yellow_button","texture":"145411f13","rect":[3,1680,335,119],"offset":[0,0],"originalSize":[335,119],"rotated":1,"capInsets":[62,32,42,58]}},{"__type__":"cc.SpriteFrame","content":{"name":"fish_ui_bottom","texture":"11373946f","rect":[3,1411,106,380],"offset":[0,0],"originalSize":[106,380],"capInsets":[41,94,41,53]}},{"__type__":"cc.SpriteFrame","content":{"name":"light_2_c","texture":"145411f13","rect":[1446,1678,200,199],"offset":[0,0],"originalSize":[200,199],"capInsets":[0,0,0,0]}},{"__type__":"cc.SpriteFrame","content":{"name":"upgraded_bg2","texture":"145411f13","rect":[83,1222,74,74],"offset":[0,0],"originalSize":[74,74],"capInsets":[16,18,14,19]}},{"__type__":"cc.SpriteFrame","content":{"name":"crystla_icon","texture":"145411f13","rect":[1105,1329,44,53],"offset":[0,0],"originalSize":[44,53],"capInsets":[0,0,0,0]}},{"__type__":"cc.SpriteFrame","content":{"name":"select_button","texture":"145411f13","rect":[1659,959,347,120],"offset":[0,0],"originalSize":[347,120],"capInsets":[0,0,0,0]}},{"__type__":"cc.SpriteFrame","content":{"name":"fishIcon0","texture":"1a48c8419","rect":[3,136,183,128],"offset":[0,0],"originalSize":[183,128],"capInsets":[0,0,0,0]}},{"__type__":"cc.SpriteFrame","content":{"name":"default_panel","texture":"d8HsitJHxOYqo801xBk8ev","rect":[0,0,20,20],"offset":[0,0],"originalSize":[20,20],"capInsets":[6,6,6,6]}},[{"__type__":"cc.Prefab","_name":"fishUI","data":{"__id__":1}},{"__type__":"cc.Node","_name":"fishUI","_children":[{"__id__":2},{"__id__":3},{"__id__":4},{"__id__":23},{"__id__":48},{"__type__":"cc.Node","_name":"noviceTestSkill","_parent":{"__id__":1},"_prefab":{"__type__":"cc.PrefabInfo","root":{"__id__":1},"asset":{"__uuid__":"9edHRw9f5Fib1tKbB1+viT"},"fileId":"2eqVJmT/dOopt9KL1Y4egS"},"_contentSize":{"__type__":"cc.Size","width":371,"height":117},"_trs":{"__type__":"TypedArray","ctor":"Float64Array","array":[8,146,0,0,0,0,1,1,1,1]}}],"_components":[{"__type__":"cc.Widget","node":{"__id__":1},"_alignFlags":45,"_left":-750,"_right":750,"_originalWidth":750,"_originalHeight":1334},{"__type__":"a62209LTKBNrqhgyAdcy3Qn","node":{"__id__":1},"fishNameLabel":{"__id__":34},"fishLevelLabel":{"__id__":11},"selectBtnNode":{"__id__":18},"selectBtnFrames":[{"__uuid__":"6eOWV2aHZEkKHfrXPLUsTt"},{"__uuid__":"2dYwfK0iBPirMBAvMihygy"},{"__uuid__":"c7u374YcpELLqxdJ8UV6s3"},{"__uuid__":"aezQb5nn9JTYNrS0by7eYZ"}],"starLabel":{"__id__":22},"selectLabel":{"__id__":20},"progressBar":{"__id__":9},"costLabel":{"__id__":16},"upGradeBtnNode":{"__id__":12},"skillArr":[{"__id__":37},{"__id__":40},{"__id__":43}],"crystlaLabel":{"__id__":51},"introduceLabel":{"__id__":33}},{"__type__":"cc.Mask","node":{"__id__":1},"_materials":[{"__uuid__":"ecpdLyjvZBwrvm+cedCcQy"}]}],"_prefab":{"__type__":"cc.PrefabInfo","root":{"__id__":1},"asset":{"__uuid__":"9edHRw9f5Fib1tKbB1+viT"},"fileId":"f3JlGLP71Iib8BDgI/jlpi"},"_contentSize":{"__type__":"cc.Size","width":750,"height":1334},"_trs":{"__type__":"TypedArray","ctor":"Float64Array","array":[-375,667,0,0,0,0,1,1,1,1]}},{"__type__":"cc.Node","_name":"fish_ui_bg","_parent":{"__id__":1},"_components":[{"__type__":"cc.Sprite","_name":"fish_ui_bg<Sprite>","node":{"__id__":2},"_materials":[{"__uuid__":"ecpdLyjvZBwrvm+cedCcQy"}],"_spriteFrame":{"__uuid__":"cbYcJ92tdHzrrW11MsmqWD"},"_type":1,"_sizeMode":0},{"__type__":"cc.Widget","node":{"__id__":2},"_alignFlags":45,"_originalWidth":750,"_originalHeight":1334}],"_prefab":{"__type__":"cc.PrefabInfo","root":{"__id__":1},"asset":{"__uuid__":"9edHRw9f5Fib1tKbB1+viT"},"fileId":"50KCJFloJJzKj7HHWjv7bQ"},"_contentSize":{"__type__":"cc.Size","width":750,"height":1334},"_trs":{"__type__":"TypedArray","ctor":"Float64Array","array":[0,0,0,0,0,0,1,1,1,1]}},{"__type__":"cc.Node","_name":"light_2","_parent":{"__id__":1},"_components":[{"__type__":"cc.Sprite","_name":"light_2<Sprite>","node":{"__id__":3},"_materials":[{"__uuid__":"ecpdLyjvZBwrvm+cedCcQy"}],"_spriteFrame":{"__uuid__":"462/epxc1OKZv4/GpKgMky"}},{"__type__":"cc.Animation","node":{"__id__":3},"_defaultClip":{"__uuid__":"61aBnG1f9HXowk0jeADisV"},"_clips":[{"__uuid__":"61aBnG1f9HXowk0jeADisV"}],"playOnLoad":true}],"_prefab":{"__type__":"cc.PrefabInfo","root":{"__id__":1},"asset":{"__uuid__":"9edHRw9f5Fib1tKbB1+viT"},"fileId":"b2rylvgkRB94nDMBZsXkA/"},"_contentSize":{"__type__":"cc.Size","width":200,"height":199},"_trs":{"__type__":"TypedArray","ctor":"Float64Array","array":[0,317.144,0,0,0,0,1,4.263,4.263,4.263]}},{"__type__":"cc.Node","_name":"bottom","_parent":{"__id__":1},"_children":[{"__id__":5},{"__id__":6},{"__id__":12},{"__id__":18},{"__id__":21}],"_components":[{"__type__":"cc.Widget","node":{"__id__":4},"_alignFlags":44,"_bottom":667}],"_prefab":{"__type__":"cc.PrefabInfo","root":{"__id__":1},"asset":{"__uuid__":"9edHRw9f5Fib1tKbB1+viT"},"fileId":"88Bln1eKJCC7V7/DVb9fVG"},"_contentSize":{"__type__":"cc.Size","width":750},"_trs":{"__type__":"TypedArray","ctor":"Float64Array","array":[0,0,0,0,0,0,1,1,1,1]}},{"__type__":"cc.Node","_name":"fish_ui_bottom","_parent":{"__id__":4},"_components":[{"__type__":"cc.Sprite","_name":"fish_ui_bottom<Sprite>","node":{"__id__":5},"_materials":[{"__uuid__":"ecpdLyjvZBwrvm+cedCcQy"}],"_spriteFrame":{"__uuid__":"35Im2pluRDL6UjhC1xboSY"},"_type":1,"_sizeMode":0}],"_prefab":{"__type__":"cc.PrefabInfo","root":{"__id__":1},"asset":{"__uuid__":"9edHRw9f5Fib1tKbB1+viT"},"fileId":"e4zPaNpCZIyLdcZ1tbDtF/"},"_contentSize":{"__type__":"cc.Size","width":606,"height":705},"_trs":{"__type__":"TypedArray","ctor":"Float64Array","array":[4,-471,0,0,0,0,1,1,1,1]}},{"__type__":"cc.Node","_name":"progress","_parent":{"__id__":4},"_children":[{"__id__":7},{"__id__":8}],"_prefab":{"__type__":"cc.PrefabInfo","root":{"__id__":1},"asset":{"__uuid__":"9edHRw9f5Fib1tKbB1+viT"},"fileId":"b7o0jk2gdEHo3ociUGUR5q"},"_trs":{"__type__":"TypedArray","ctor":"Float64Array","array":[0,57.356,0,0,0,0,1,1,1,1]}},{"__type__":"cc.Node","_name":"egg_progress_bg","_parent":{"__id__":6},"_components":[{"__type__":"cc.Sprite","_name":"egg_progress_bg<Sprite>","node":{"__id__":7},"_materials":[{"__uuid__":"ecpdLyjvZBwrvm+cedCcQy"}],"_spriteFrame":{"__uuid__":"16oFMNBs9KXI1OveWs46ny"},"_type":1,"_sizeMode":0}],"_prefab":{"__type__":"cc.PrefabInfo","root":{"__id__":1},"asset":{"__uuid__":"9edHRw9f5Fib1tKbB1+viT"},"fileId":"9fkkrquEJNk7RazRuTabv2"},"_color":{"__type__":"cc.Color","r":115,"g":245,"b":245},"_contentSize":{"__type__":"cc.Size","width":672,"height":125},"_trs":{"__type__":"TypedArray","ctor":"Float64Array","array":[1,-267.972,0,0,0,0,1,0.8,0.8,0.8]}},{"__type__":"cc.Node","_name":"mask","_parent":{"__id__":6},"_children":[{"__id__":9}],"_components":[{"__type__":"cc.Mask","_name":"mask<Mask>","node":{"__id__":8},"_materials":[{"__uuid__":"ecpdLyjvZBwrvm+cedCcQy"}],"_spriteFrame":{"__uuid__":"f6zOKFWPhMEacA/+hQ1NE5"},"_type":2}],"_prefab":{"__type__":"cc.PrefabInfo","root":{"__id__":1},"asset":{"__uuid__":"9edHRw9f5Fib1tKbB1+viT"},"fileId":"5atWkbp6JFvo6xXa1nUmaK"},"_contentSize":{"__type__":"cc.Size","width":647,"height":107},"_trs":{"__type__":"TypedArray","ctor":"Float64Array","array":[0,-266.566,0,0,0,0,1,1,1,1]}},{"__type__":"cc.Node","_name":"egg_progress_bar","_parent":{"__id__":8},"_children":[{"__id__":10}],"_components":[{"__type__":"cc.Sprite","_name":"egg_progress_bar<Sprite>","node":{"__id__":9},"_materials":[{"__uuid__":"ecpdLyjvZBwrvm+cedCcQy"}],"_spriteFrame":{"__uuid__":"f6zOKFWPhMEacA/+hQ1NE5"},"_type":1,"_sizeMode":0}],"_prefab":{"__type__":"cc.PrefabInfo","root":{"__id__":1},"asset":{"__uuid__":"9edHRw9f5Fib1tKbB1+viT"},"fileId":"99mUDK0XNEcbxbw7c4YGwQ"},"_contentSize":{"__type__":"cc.Size","height":107},"_anchorPoint":{"__type__":"cc.Vec2","y":0.5},"_trs":{"__type__":"TypedArray","ctor":"Float64Array","array":[-259,0,0,0,0,0,1,0.8,0.8,0.8]}},{"__type__":"cc.Node","_name":"fish_level_label","_parent":{"__id__":9},"_components":[{"__id__":11}],"_prefab":{"__type__":"cc.PrefabInfo","root":{"__id__":1},"asset":{"__uuid__":"9edHRw9f5Fib1tKbB1+viT"},"fileId":"0ceq/o5DZIEYQwZ60AdsfV"},"_contentSize":{"__type__":"cc.Size","width":74.7,"height":60.48},"_trs":{"__type__":"TypedArray","ctor":"Float64Array","array":[323.422,8.288,0,0,0,0,1,1.25,1.25,1.25]}},{"__type__":"cc.Label","_name":"fish_level_label<Label>","node":{"__id__":10},"_materials":[{"__uuid__":"ecpdLyjvZBwrvm+cedCcQy"}],"_useOriginalSize":false,"_string":"1级","_N$string":"1级","_fontSize":48,"_lineHeight":48,"_N$horizontalAlign":1,"_N$verticalAlign":1},{"__type__":"cc.Node","_name":"yellow_button","_parent":{"__id__":4},"_children":[{"__id__":13},{"__id__":17}],"_components":[{"__type__":"cc.Sprite","_name":"yellow_button<Sprite>","node":{"__id__":12},"_materials":[{"__uuid__":"ecpdLyjvZBwrvm+cedCcQy"}],"_spriteFrame":{"__uuid__":"2dYwfK0iBPirMBAvMihygy"},"_type":1,"_sizeMode":0},{"__type__":"cc.Button","node":{"__id__":12},"zoomScale":0.8,"clickEvents":[{"__type__":"cc.ClickEvent","target":{"__id__":1},"_componentId":"a62209LTKBNrqhgyAdcy3Qn","handler":"onUpGradeBtnClick"}],"_N$transition":3,"transition":3}],"_prefab":{"__type__":"cc.PrefabInfo","root":{"__id__":1},"asset":{"__uuid__":"9edHRw9f5Fib1tKbB1+viT"},"fileId":"48ypYV2FhP5oRQOHWcdi5e"},"_contentSize":{"__type__":"cc.Size","width":427,"height":139},"_trs":{"__type__":"TypedArray","ctor":"Float64Array","array":[0,-366.15,0,0,0,0,1,1,1,1]}},{"__type__":"cc.Node","_name":"upgraded_bg2","_parent":{"__id__":12},"_children":[{"__id__":14},{"__id__":15}],"_components":[{"__type__":"cc.Sprite","_name":"upgraded_bg2<Sprite>","node":{"__id__":13},"_materials":[{"__uuid__":"ecpdLyjvZBwrvm+cedCcQy"}],"_spriteFrame":{"__uuid__":"4f7c1xbj5N/q+NmCwRcsvK"},"_type":1,"_sizeMode":0}],"_prefab":{"__type__":"cc.PrefabInfo","root":{"__id__":1},"asset":{"__uuid__":"9edHRw9f5Fib1tKbB1+viT"},"fileId":"1aeDK/loRPCb2NiaPsOUKN"},"_contentSize":{"__type__":"cc.Size","width":161.8,"height":74},"_trs":{"__type__":"TypedArray","ctor":"Float64Array","array":[101,14.8,0,0,0,0,1,1,1,1]}},{"__type__":"cc.Node","_name":"gold_icon","_parent":{"__id__":13},"_components":[{"__type__":"cc.Sprite","_name":"gold_icon<Sprite>","node":{"__id__":14},"_materials":[{"__uuid__":"ecpdLyjvZBwrvm+cedCcQy"}],"_spriteFrame":{"__uuid__":"f6wQ+drKZC77hij8bYFLOF"}}],"_prefab":{"__type__":"cc.PrefabInfo","root":{"__id__":1},"asset":{"__uuid__":"9edHRw9f5Fib1tKbB1+viT"},"fileId":"48DtaqobBG3K15ijfCHOaE"},"_contentSize":{"__type__":"cc.Size","width":40,"height":44},"_trs":{"__type__":"TypedArray","ctor":"Float64Array","array":[48.792,2.602,0,0,0,0,1,1,1,1]}},{"__type__":"cc.Node","_name":"cost_label","_parent":{"__id__":13},"_components":[{"__id__":16}],"_prefab":{"__type__":"cc.PrefabInfo","root":{"__id__":1},"asset":{"__uuid__":"9edHRw9f5Fib1tKbB1+viT"},"fileId":"87Zzp6ioFDEIiptJDCBNrm"},"_contentSize":{"__type__":"cc.Size","width":103.4,"height":37.5},"_anchorPoint":{"__type__":"cc.Vec2","x":1,"y":0.5},"_trs":{"__type__":"TypedArray","ctor":"Float64Array","array":[24.1,23,0,0,0,0,1,1,1,1]}},{"__type__":"cc.Label","_name":"cost_label<Label>","node":{"__id__":15},"_materials":[{"__uuid__":"ecpdLyjvZBwrvm+cedCcQy"}],"_useOriginalSize":false,"_string":"50","_N$string":"50","_fontSize":30,"_N$file":{"__uuid__":"7aouBqPjxBx7fV9hSp+FxB"},"_isSystemFontUsed":false,"_spacingX":-8,"_N$horizontalAlign":2,"_N$verticalAlign":1,"_N$overflow":2},{"__type__":"cc.Node","_name":"New Label","_parent":{"__id__":12},"_components":[{"__type__":"cc.Label","_name":"New Label<Label>","node":{"__id__":17},"_materials":[{"__uuid__":"ecpdLyjvZBwrvm+cedCcQy"}],"_useOriginalSize":false,"_string":"喂养","_N$string":"喂养","_fontSize":48,"_lineHeight":48,"_N$horizontalAlign":1,"_N$verticalAlign":1,"_N$cacheMode":2}],"_prefab":{"__type__":"cc.PrefabInfo","root":{"__id__":1},"asset":{"__uuid__":"9edHRw9f5Fib1tKbB1+viT"},"fileId":"5bc6uCUuRFwI8ui6jpAKoD"},"_color":{"__type__":"cc.Color","r":96,"g":36},"_contentSize":{"__type__":"cc.Size","width":96,"height":48},"_trs":{"__type__":"TypedArray","ctor":"Float64Array","array":[-86.001,17.267,0,0,0,0,1,1,1,1]}},{"__type__":"cc.Node","_name":"select_button","_parent":{"__id__":4},"_children":[{"__id__":19}],"_components":[{"__type__":"cc.Sprite","_name":"select_button<Sprite>","node":{"__id__":18},"_materials":[{"__uuid__":"ecpdLyjvZBwrvm+cedCcQy"}],"_spriteFrame":{"__uuid__":"6eOWV2aHZEkKHfrXPLUsTt"},"_type":1,"_sizeMode":0},{"__type__":"cc.Button","node":{"__id__":18},"zoomScale":0.8,"clickEvents":[{"__type__":"cc.ClickEvent","target":{"__id__":1},"_componentId":"a62209LTKBNrqhgyAdcy3Qn","handler":"onSelectBtnClick"}],"_N$transition":3,"transition":3}],"_prefab":{"__type__":"cc.PrefabInfo","root":{"__id__":1},"asset":{"__uuid__":"9edHRw9f5Fib1tKbB1+viT"},"fileId":"1fmZIa+dNBPae/TzT/g/W2"},"_contentSize":{"__type__":"cc.Size","width":347,"height":120},"_trs":{"__type__":"TypedArray","ctor":"Float64Array","array":[0,-28.763,0,0,0,0,1,1,1,1]}},{"__type__":"cc.Node","_name":"select_label","_parent":{"__id__":18},"_components":[{"__id__":20}],"_prefab":{"__type__":"cc.PrefabInfo","root":{"__id__":1},"asset":{"__uuid__":"9edHRw9f5Fib1tKbB1+viT"},"fileId":"aabNg6AgZPuqY0k5YJdaGZ"},"_contentSize":{"__type__":"cc.Size","width":126,"height":42},"_trs":{"__type__":"TypedArray","ctor":"Float64Array","array":[0,19.774,0,0,0,0,1,1,1,1]}},{"__type__":"cc.Label","_name":"select_label<Label>","node":{"__id__":19},"_materials":[{"__uuid__":"ecpdLyjvZBwrvm+cedCcQy"}],"_useOriginalSize":false,"_string":"已选择","_N$string":"已选择","_fontSize":42,"_lineHeight":42,"_N$horizontalAlign":1,"_N$verticalAlign":1,"_N$cacheMode":2},{"__type__":"cc.Node","_name":"star_label","_parent":{"__id__":4},"_components":[{"__id__":22}],"_prefab":{"__type__":"cc.PrefabInfo","root":{"__id__":1},"asset":{"__uuid__":"9edHRw9f5Fib1tKbB1+viT"},"fileId":"a7lMvwx0hPdK/xm6O7Tj9/"},"_contentSize":{"__type__":"cc.Size","width":85.72,"height":40},"_trs":{"__type__":"TypedArray","ctor":"Float64Array","array":[0,71.131,0,0,0,0,1,1,1,1]}},{"__type__":"cc.Label","_name":"star_label<Label>","node":{"__id__":21},"_materials":[{"__uuid__":"ecpdLyjvZBwrvm+cedCcQy"}],"_useOriginalSize":false,"_string":"1/20","_N$string":"1/20","_N$file":{"__uuid__":"8f0P8tLoBPipzRLk4E196R"},"_isSystemFontUsed":false,"_N$horizontalAlign":1,"_N$verticalAlign":1,"_N$cacheMode":2},{"__type__":"cc.Node","_name":"center","_parent":{"__id__":1},"_children":[{"__id__":24},{"__id__":25},{"__id__":31},{"__id__":35},{"__id__":45}],"_components":[{"__type__":"cc.Widget","node":{"__id__":23},"_alignFlags":45,"_top":-88.96,"_bottom":88.96}],"_prefab":{"__type__":"cc.PrefabInfo","root":{"__id__":1},"asset":{"__uuid__":"9edHRw9f5Fib1tKbB1+viT"},"fileId":"4b0KLOIQpPvKexn51H1Nkq"},"_contentSize":{"__type__":"cc.Size","width":750,"height":1334},"_trs":{"__type__":"TypedArray","ctor":"Float64Array","array":[0,88.96000000000004,0,0,0,0,1,1,1,1]}},{"__type__":"cc.Node","_name":"touchBg","_parent":{"__id__":23},"_components":[{"__type__":"cc.Sprite","_name":"background<Sprite>","node":{"__id__":24},"_materials":[{"__uuid__":"ecpdLyjvZBwrvm+cedCcQy"}],"_spriteFrame":{"__uuid__":"9bvaMerUlDyary99mJa6xp"},"_type":1,"_sizeMode":0}],"_prefab":{"__type__":"cc.PrefabInfo","root":{"__id__":1},"asset":{"__uuid__":"9edHRw9f5Fib1tKbB1+viT"},"fileId":"54XfADk8tGZLOvBpk2hyEd"},"_opacity":135.91500000000002,"_color":{"__type__":"cc.Color","r":9,"g":30,"b":68},"_contentSize":{"__type__":"cc.Size","width":753,"height":223},"_trs":{"__type__":"TypedArray","ctor":"Float64Array","array":[0,242,0,0,0,0,1,1,1,1]}},{"__type__":"cc.Node","_name":"fish_PageView","_parent":{"__id__":23},"_children":[{"__id__":26},{"__id__":28}],"_active":false,"_components":[{"__id__":30}],"_prefab":{"__type__":"cc.PrefabInfo","root":{"__id__":1},"asset":{"__uuid__":"9edHRw9f5Fib1tKbB1+viT"},"fileId":"53OwyNjW1CdpJd+vOk1H6t"},"_contentSize":{"__type__":"cc.Size","width":750,"height":220},"_trs":{"__type__":"TypedArray","ctor":"Float64Array","array":[0,242,0,0,0,0,1,1,1,1]}},{"__type__":"cc.Node","_name":"view","_parent":{"__id__":25},"_children":[{"__id__":27}],"_components":[{"__type__":"cc.Mask","_name":"view<Mask>","node":{"__id__":26},"_materials":[{"__uuid__":"ecpdLyjvZBwrvm+cedCcQy"}],"_N$alphaThreshold":0}],"_prefab":{"__type__":"cc.PrefabInfo","root":{"__id__":1},"asset":{"__uuid__":"9edHRw9f5Fib1tKbB1+viT"},"fileId":"1afJHsYFlHu6S+83Ufu+Gw"},"_contentSize":{"__type__":"cc.Size","width":750,"height":215},"_trs":{"__type__":"TypedArray","ctor":"Float64Array","array":[0,0,0,0,0,0,1,1,1,1]}},{"__type__":"cc.Node","_name":"content","_parent":{"__id__":26},"_components":[{"__type__":"cc.Layout","node":{"__id__":27},"_layoutSize":{"__type__":"cc.Size","width":750,"height":233},"_resize":1,"_N$layoutType":1,"_N$spacingY":15}],"_prefab":{"__type__":"cc.PrefabInfo","root":{"__id__":1},"asset":{"__uuid__":"9edHRw9f5Fib1tKbB1+viT"},"fileId":"92NTL0oXtDA6ZEdr86b8gm"},"_contentSize":{"__type__":"cc.Size","width":750,"height":233},"_anchorPoint":{"__type__":"cc.Vec2","y":0.5},"_trs":{"__type__":"TypedArray","ctor":"Float64Array","array":[-375,0,0,0,0,0,1,1,1,1]}},{"__type__":"cc.Node","_name":"indicator","_parent":{"__id__":25},"_components":[{"__id__":29}],"_prefab":{"__type__":"cc.PrefabInfo","root":{"__id__":1},"asset":{"__uuid__":"9edHRw9f5Fib1tKbB1+viT"},"fileId":"de3NZkPyVBF6UEAVkjz9vp"},"_contentSize":{"__type__":"cc.Size","width":100,"height":27},"_trs":{"__type__":"TypedArray","ctor":"Float64Array","array":[0,-91.734,0,0,0,0,1,1,1,1]}},{"__type__":"cc.PageViewIndicator","node":{"__id__":28},"_pageView":{"__id__":30},"spriteFrame":{"__uuid__":"245Fl+68lE4LoiIEni3ItT"},"cellSize":{"__type__":"cc.Size","width":10,"height":10},"spacing":10},{"__type__":"cc.PageView","node":{"__id__":25},"bounceDuration":0.5,"_N$content":{"__id__":27},"content":{"__id__":27},"pageEvents":[{"__type__":"cc.ClickEvent","target":{"__id__":1},"_componentId":"08ab3iy8k9OxIaJ2e0LUfw+","handler":"fishPageView"}],"_N$indicator":{"__id__":29}},{"__type__":"cc.Node","_name":"fish_name","_parent":{"__id__":23},"_children":[{"__id__":32}],"_components":[{"__id__":34}],"_prefab":{"__type__":"cc.PrefabInfo","root":{"__id__":1},"asset":{"__uuid__":"9edHRw9f5Fib1tKbB1+viT"},"fileId":"a8LsgCbCBFeobLYNNsy5Vm"},"_contentSize":{"__type__":"cc.Size","width":262,"height":60},"_trs":{"__type__":"TypedArray","ctor":"Float64Array","array":[0,504.153,0,0,0,0,1,1,1,1]}},{"__type__":"cc.Node","_name":"fishIntroduce","_parent":{"__id__":31},"_components":[{"__id__":33}],"_prefab":{"__type__":"cc.PrefabInfo","root":{"__id__":1},"asset":{"__uuid__":"9edHRw9f5Fib1tKbB1+viT"},"fileId":"b8JajImoJJhIzj3CY37i3M"},"_contentSize":{"__type__":"cc.Size","width":64,"height":40.32},"_trs":{"__type__":"TypedArray","ctor":"Float64Array","array":[0,-116.768,0,0,0,0,1,1,1,1]}},{"__type__":"cc.Label","_name":"fish_breed<Label>","node":{"__id__":32},"_materials":[{"__uuid__":"ecpdLyjvZBwrvm+cedCcQy"}],"_useOriginalSize":false,"_string":"一般","_N$string":"一般","_fontSize":32,"_lineHeight":32,"_N$horizontalAlign":1,"_N$verticalAlign":1},{"__type__":"cc.Label","_name":"fish_name<Label>","node":{"__id__":31},"_materials":[{"__uuid__":"ecpdLyjvZBwrvm+cedCcQy"}],"_useOriginalSize":false,"_string":"珊瑚妞妞","_N$string":"珊瑚妞妞","_fontSize":32,"_lineHeight":60,"_N$file":{"__uuid__":"15go0CoXVCtLI6dorvme2U"},"_isSystemFontUsed":false,"_spacingX":-8,"_N$horizontalAlign":1,"_N$verticalAlign":1},{"__type__":"cc.Node","_name":"skill","_parent":{"__id__":23},"_children":[{"__id__":36},{"__id__":39},{"__id__":42}],"_prefab":{"__type__":"cc.PrefabInfo","root":{"__id__":1},"asset":{"__uuid__":"9edHRw9f5Fib1tKbB1+viT"},"fileId":"8e1FTKDv5EFbmnRaE8UIh0"},"_trs":{"__type__":"TypedArray","ctor":"Float64Array","array":[0,53.322,0,0,0,0,1,1,1,1]}},{"__type__":"cc.Node","_name":"skill_floor1","_parent":{"__id__":35},"_children":[{"__id__":37},{"__id__":38}],"_components":[{"__type__":"cc.Sprite","_name":"skill_floor1<Sprite>","node":{"__id__":36},"_materials":[{"__uuid__":"ecpdLyjvZBwrvm+cedCcQy"}],"_spriteFrame":{"__uuid__":"1e2npSD0ZLMr99VZ+3nCf6"}},{"__type__":"cc.Button","node":{"__id__":36},"zoomScale":0.8,"clickEvents":[{"__type__":"cc.ClickEvent","target":{"__id__":1},"_componentId":"a62209LTKBNrqhgyAdcy3Qn","handler":"onSkillBtnClick","customEventData":"skill1"}],"_N$transition":3,"transition":3}],"_prefab":{"__type__":"cc.PrefabInfo","root":{"__id__":1},"asset":{"__uuid__":"9edHRw9f5Fib1tKbB1+viT"},"fileId":"b2z4VyF5dD0rXTjoN7Q3Xs"},"_contentSize":{"__type__":"cc.Size","width":74,"height":74},"_trs":{"__type__":"TypedArray","ctor":"Float64Array","array":[-135,0,0,0,0,0,1,1,1,1]}},{"__type__":"cc.Node","_name":"skill1","_parent":{"__id__":36},"_components":[{"__type__":"cc.Sprite","_name":"skill1<Sprite>","node":{"__id__":37},"_materials":[{"__uuid__":"ecpdLyjvZBwrvm+cedCcQy"}],"_spriteFrame":{"__uuid__":"edGKAvjFxL7YdGaxDDGWfG"}}],"_prefab":{"__type__":"cc.PrefabInfo","root":{"__id__":1},"asset":{"__uuid__":"9edHRw9f5Fib1tKbB1+viT"},"fileId":"36WoAGnDpMYYOflzUbgY3F"},"_contentSize":{"__type__":"cc.Size","width":120,"height":120},"_trs":{"__type__":"TypedArray","ctor":"Float64Array","array":[0,0,0,0,0,0,1,0.45,0.45,1]}},{"__type__":"cc.Node","_name":"skill_help","_parent":{"__id__":36},"_components":[{"__type__":"cc.Sprite","_name":"skill_help<Sprite>","node":{"__id__":38},"_materials":[{"__uuid__":"ecpdLyjvZBwrvm+cedCcQy"}],"_spriteFrame":{"__uuid__":"a0Rocd04dCL66f0oyMGktY"},"_sizeMode":2,"_isTrimmedMode":false}],"_prefab":{"__type__":"cc.PrefabInfo","root":{"__id__":1},"asset":{"__uuid__":"9edHRw9f5Fib1tKbB1+viT"},"fileId":"eeWxzjSIJIpI+LAXgJgpS5"},"_contentSize":{"__type__":"cc.Size","width":39,"height":42},"_trs":{"__type__":"TypedArray","ctor":"Float64Array","array":[32.064,31.045,0,0,0,0,1,1,1,1]}},{"__type__":"cc.Node","_name":"skill_floor2","_parent":{"__id__":35},"_children":[{"__id__":40},{"__id__":41}],"_components":[{"__type__":"cc.Sprite","_name":"skill_floor2<Sprite>","node":{"__id__":39},"_materials":[{"__uuid__":"ecpdLyjvZBwrvm+cedCcQy"}],"_spriteFrame":{"__uuid__":"1e2npSD0ZLMr99VZ+3nCf6"}},{"__type__":"cc.Button","node":{"__id__":39},"zoomScale":0.8,"clickEvents":[{"__type__":"cc.ClickEvent","target":{"__id__":1},"_componentId":"a62209LTKBNrqhgyAdcy3Qn","handler":"onSkillBtnClick","customEventData":"skill2"}],"_N$transition":3,"transition":3}],"_prefab":{"__type__":"cc.PrefabInfo","root":{"__id__":1},"asset":{"__uuid__":"9edHRw9f5Fib1tKbB1+viT"},"fileId":"91oKAnurZAzriqrT3Pe4d5"},"_contentSize":{"__type__":"cc.Size","width":74,"height":74},"_trs":{"__type__":"TypedArray","ctor":"Float64Array","array":[0,0,0,0,0,0,1,1,1,1]}},{"__type__":"cc.Node","_name":"skill2","_parent":{"__id__":39},"_components":[{"__type__":"cc.Sprite","_name":"skill2<Sprite>","node":{"__id__":40},"_materials":[{"__uuid__":"ecpdLyjvZBwrvm+cedCcQy"}],"_spriteFrame":{"__uuid__":"d00+hk4NRBeKzhIvhugG45"}}],"_prefab":{"__type__":"cc.PrefabInfo","root":{"__id__":1},"asset":{"__uuid__":"9edHRw9f5Fib1tKbB1+viT"},"fileId":"c2fMrzluFKDptLolzRiyGx"},"_contentSize":{"__type__":"cc.Size","width":134,"height":111},"_trs":{"__type__":"TypedArray","ctor":"Float64Array","array":[0,0,0,0,0,0,1,0.393,0.393,0.873]}},{"__type__":"cc.Node","_name":"skill_help","_parent":{"__id__":39},"_components":[{"__type__":"cc.Sprite","_name":"skill_help<Sprite>","node":{"__id__":41},"_materials":[{"__uuid__":"ecpdLyjvZBwrvm+cedCcQy"}],"_spriteFrame":{"__uuid__":"a0Rocd04dCL66f0oyMGktY"},"_sizeMode":2,"_isTrimmedMode":false}],"_prefab":{"__type__":"cc.PrefabInfo","root":{"__id__":1},"asset":{"__uuid__":"9edHRw9f5Fib1tKbB1+viT"},"fileId":"16cvu0/vdNOIOiY2G1GMzT"},"_contentSize":{"__type__":"cc.Size","width":39,"height":42},"_trs":{"__type__":"TypedArray","ctor":"Float64Array","array":[32.064,31.045,0,0,0,0,1,1,1,1]}},{"__type__":"cc.Node","_name":"skill_floor3","_parent":{"__id__":35},"_children":[{"__id__":43},{"__id__":44}],"_components":[{"__type__":"cc.Sprite","_name":"skill_floor3<Sprite>","node":{"__id__":42},"_materials":[{"__uuid__":"ecpdLyjvZBwrvm+cedCcQy"}],"_spriteFrame":{"__uuid__":"1e2npSD0ZLMr99VZ+3nCf6"}},{"__type__":"cc.Button","node":{"__id__":42},"zoomScale":0.8,"clickEvents":[{"__type__":"cc.ClickEvent","target":{"__id__":1},"_componentId":"a62209LTKBNrqhgyAdcy3Qn","handler":"onSkillBtnClick","customEventData":"skill3"}],"_N$transition":3,"transition":3}],"_prefab":{"__type__":"cc.PrefabInfo","root":{"__id__":1},"asset":{"__uuid__":"9edHRw9f5Fib1tKbB1+viT"},"fileId":"66/POjN8ZMTZtz9A3dbCew"},"_contentSize":{"__type__":"cc.Size","width":74,"height":74},"_trs":{"__type__":"TypedArray","ctor":"Float64Array","array":[135,0,0,0,0,0,1,1,1,1]}},{"__type__":"cc.Node","_name":"skill3","_parent":{"__id__":42},"_components":[{"__type__":"cc.Sprite","_name":"skill3<Sprite>","node":{"__id__":43},"_materials":[{"__uuid__":"ecpdLyjvZBwrvm+cedCcQy"}],"_spriteFrame":{"__uuid__":"1ekrYbwWNOGoeyORWHx6oj"}}],"_prefab":{"__type__":"cc.PrefabInfo","root":{"__id__":1},"asset":{"__uuid__":"9edHRw9f5Fib1tKbB1+viT"},"fileId":"59QQX6SQxH4Z0uq3XE0rNP"},"_contentSize":{"__type__":"cc.Size","width":122,"height":122},"_trs":{"__type__":"TypedArray","ctor":"Float64Array","array":[0,0,0,0,0,0,1,0.45,0.45,0.999]}},{"__type__":"cc.Node","_name":"skill_help","_parent":{"__id__":42},"_components":[{"__type__":"cc.Sprite","_name":"skill_help<Sprite>","node":{"__id__":44},"_materials":[{"__uuid__":"ecpdLyjvZBwrvm+cedCcQy"}],"_spriteFrame":{"__uuid__":"a0Rocd04dCL66f0oyMGktY"},"_sizeMode":2,"_isTrimmedMode":false}],"_prefab":{"__type__":"cc.PrefabInfo","root":{"__id__":1},"asset":{"__uuid__":"9edHRw9f5Fib1tKbB1+viT"},"fileId":"86wKEbNR1PvIVjqC+5ALBj"},"_contentSize":{"__type__":"cc.Size","width":39,"height":42},"_trs":{"__type__":"TypedArray","ctor":"Float64Array","array":[32.064,31.045,0,0,0,0,1,1,1,1]}},{"__type__":"cc.Node","_name":"touchScroll","_parent":{"__id__":23},"_children":[{"__id__":46}],"_components":[{"__type__":"009a3MR6oJOE5JWOfcXvtPt","node":{"__id__":45}}],"_prefab":{"__type__":"cc.PrefabInfo","root":{"__id__":1},"asset":{"__uuid__":"9edHRw9f5Fib1tKbB1+viT"},"fileId":"bar46ZaSlGm5+prGFca5+Y"},"_contentSize":{"__type__":"cc.Size","width":750,"height":223},"_trs":{"__type__":"TypedArray","ctor":"Float64Array","array":[0,242,0,0,0,0,1,1,1,1]}},{"__type__":"cc.Node","_name":"content","_parent":{"__id__":45},"_children":[{"__id__":47}],"_prefab":{"__type__":"cc.PrefabInfo","root":{"__id__":1},"asset":{"__uuid__":"9edHRw9f5Fib1tKbB1+viT"},"fileId":"38qBANHNtBGK0sxgUrPcka"},"_contentSize":{"__type__":"cc.Size","width":183,"height":128},"_trs":{"__type__":"TypedArray","ctor":"Float64Array","array":[0,0,0,0,0,0,1,0.8,0.8,0.8]}},{"__type__":"cc.Node","_name":"icon","_parent":{"__id__":46},"_components":[{"__type__":"cc.Sprite","_name":"New Sprite(Splash)<Sprite>","node":{"__id__":47},"_materials":[{"__uuid__":"ecpdLyjvZBwrvm+cedCcQy"}],"_spriteFrame":{"__uuid__":"87NVRea+VC1pZVSO+MJYQv"},"_sizeMode":2}],"_prefab":{"__type__":"cc.PrefabInfo","root":{"__id__":1},"asset":{"__uuid__":"9edHRw9f5Fib1tKbB1+viT"},"fileId":"c32y9jUkVNPrG2DT2HH1CM"},"_contentSize":{"__type__":"cc.Size","width":183,"height":128},"_trs":{"__type__":"TypedArray","ctor":"Float64Array","array":[0,0,0,0,0,0,1,0.8,0.8,1]}},{"__type__":"cc.Node","_name":"top","_parent":{"__id__":1},"_children":[{"__id__":49}],"_components":[{"__type__":"cc.Widget","node":{"__id__":48},"_alignFlags":41,"_left":375,"_right":375,"_top":97}],"_prefab":{"__type__":"cc.PrefabInfo","root":{"__id__":1},"asset":{"__uuid__":"9edHRw9f5Fib1tKbB1+viT"},"fileId":"73m2y6MBdGr4fVYMXz3/ib"},"_trs":{"__type__":"TypedArray","ctor":"Float64Array","array":[0,570,0,0,0,0,1,1,1,1]}},{"__type__":"cc.Node","_name":"crystla_icon","_parent":{"__id__":48},"_children":[{"__id__":50}],"_components":[{"__type__":"cc.Sprite","_name":"crystla_icon<Sprite>","node":{"__id__":49},"_materials":[{"__uuid__":"ecpdLyjvZBwrvm+cedCcQy"}],"_spriteFrame":{"__uuid__":"511WxFullJWrNWqpe99VjQ"}}],"_prefab":{"__type__":"cc.PrefabInfo","root":{"__id__":1},"asset":{"__uuid__":"9edHRw9f5Fib1tKbB1+viT"},"fileId":"ff/cxgqIZIDJTdcAMKInZI"},"_contentSize":{"__type__":"cc.Size","width":44,"height":53},"_trs":{"__type__":"TypedArray","ctor":"Float64Array","array":[-328.384,0,0,0,0,0,1,1,1,1]}},{"__type__":"cc.Node","_name":"crystla_label","_parent":{"__id__":49},"_components":[{"__id__":51}],"_prefab":{"__type__":"cc.PrefabInfo","root":{"__id__":1},"asset":{"__uuid__":"9edHRw9f5Fib1tKbB1+viT"},"fileId":"8b2o/doQ9C547tV8jP9x/Q"},"_contentSize":{"__type__":"cc.Size","width":32,"height":40},"_anchorPoint":{"__type__":"cc.Vec2","y":0.5},"_trs":{"__type__":"TypedArray","ctor":"Float64Array","array":[31.877,23.544,0,0,0,0,1,1,1,1]}},{"__type__":"cc.Label","_name":"crystla_label<Label>","node":{"__id__":50},"_materials":[{"__uuid__":"ecpdLyjvZBwrvm+cedCcQy"}],"_useOriginalSize":false,"_string":"0","_N$string":"0","_fontSize":32,"_N$file":{"__uuid__":"7aouBqPjxBx7fV9hSp+FxB"},"_isSystemFontUsed":false,"_spacingX":-8,"_N$horizontalAlign":1,"_N$verticalAlign":1}],{"__type__":"cc.SpriteFrame","content":{"name":"skill_help","texture":"1f90e2f9a","rect":[1774,2002,39,42],"offset":[0,0],"originalSize":[39,42],"capInsets":[0,0,0,0]}},{"__type__":"cc.SpriteFrame","content":{"name":"select_button_lock","texture":"145411f13","rect":[1659,1085,347,120],"offset":[0,0],"originalSize":[347,120],"capInsets":[0,0,0,0]}},{"__type__":"cc.SpriteFrame","content":{"name":"select_button_video","texture":"145411f13","rect":[1659,1211,347,120],"offset":[0,0],"originalSize":[347,120],"capInsets":[0,0,0,0]}},{"__type__":"cc.SpriteFrame","content":{"name":"fish_ui_bg","texture":"145411f13","rect":[1776,1680,64,64],"offset":[0,0],"originalSize":[64,64],"capInsets":[0,0,0,0]}},{"__type__":"cc.SpriteFrame","content":{"name":"skill2","texture":"145411f13","rect":[1162,1276,134,111],"offset":[0,0],"originalSize":[134,111],"rotated":1,"capInsets":[0,0,0,0]}},{"__type__":"cc.SpriteFrame","content":{"name":"skill1","texture":"145411f13","rect":[1577,1883,120,120],"offset":[0,0],"originalSize":[120,120],"capInsets":[0,0,0,0]}},{"__type__":"cc.SpriteFrame","content":{"name":"gold_icon","texture":"145411f13","rect":[484,1496,40,44],"offset":[0,0],"originalSize":[40,44],"rotated":1,"capInsets":[0,0,0,0]}},{"__type__":"cc.SpriteFrame","content":{"name":"egg_progress_bar","texture":"145411f13","rect":[3,531,580,107],"offset":[0,0],"originalSize":[580,107],"capInsets":[68,0,76,0]}}]